new_calculator/__init__.py
new_calculator/functions.py
new_calculator-0.2.dist-info/LICENSE.txt
new_calculator-0.2.dist-info/METADATA
new_calculator-0.2.dist-info/WHEEL
new_calculator-0.2.dist-info/entry_points.txt
new_calculator-0.2.dist-info/top_level.txt
new_calculator-0.2.dist-info/RECORD
