Metadata-Version: 2.1
Name: new-calculator
Version: 0.2
Summary: Demo package for calculate
Author: ngnambka00
Author-email: ngnambka00@gmail.com
Classifier: Programming Language :: Python :: 3
Classifier: License :: OSI Approved :: MIT License
Classifier: Operating System :: OS Independent
License-File: LICENSE.txt
